MANIFEST.in
setup.py
briefdruckzentrum/__init__.py
briefdruckzentrum/adapters.py
briefdruckzentrum/api.py
python_briefdruckzentrum.egg-info/PKG-INFO
python_briefdruckzentrum.egg-info/SOURCES.txt
python_briefdruckzentrum.egg-info/dependency_links.txt
python_briefdruckzentrum.egg-info/requires.txt
python_briefdruckzentrum.egg-info/top_level.txt