Metadata-Version: 1.1
Name: python-briefdruckzentrum
Version: 0.1.4
Summary: a lightweight python wrapper for briefdruckzentrum.de API
Home-page: https://github.com/Thermondo/python-briefdruckzentrum
Author: codingjoe
Author-email: info@johanneshoppe.com
License: MIT
Platform: UNKNOWN
Classifier: Development Status :: 2 - Pre-Alpha
Classifier: Topic :: Printing
Classifier: Environment :: Web Environment
Classifier: Topic :: Office/Business :: Financial :: Accounting
Classifier: Intended Audience :: Developers
Classifier: Intended Audience :: Financial and Insurance Industry
Classifier: License :: OSI Approved :: MIT License
Classifier: Operating System :: OS Independent
Classifier: Programming Language :: Python
Classifier: Topic :: Software Development
Classifier: Programming Language :: Python :: 2.6
Classifier: Programming Language :: Python :: 2.7
Classifier: Programming Language :: Python :: 3.2
Classifier: Programming Language :: Python :: 3.3
